{
  "question": [1992],
  "answer": [2559, 264],
  "hi": [489],
  "how": [334, 119],
  "are": [754],
  "you": [266],
  "doing": [1876],
  "i": [105],
  "m": [109],
  "fine": [537, 341],
  "about": [1342],
  "yourself": [266, 2341],
  "pretty": [2835],
  "good": [344, 111, 100],
  "thanks": [2213],
  "for": [2127, 114],
  "asking": [781, 1713, 110, 103],
  "no": [293],
  "problem": [798],
  "so": [360],
  "have": [1465],
  "been": [345, 282],
  "ve": [568],
  "great": [1957, 290, 116],
  "what": [318, 286],
  "in": [261],
  "school": [817],
  "right": [646],
  "now": [747],
  "do": [336],
  "go": [344],
  "to": [363],
  "pcc": [2662, 99],
  "like": [1048],
  "it": [287],
  "there": [612],
  "s": [115],
  "okay": [592],
  "a": [97],
  "really": [354, 367, 560],
  "big": [1944],
  "campus": [447, 109, 572, 115],
  "luck": [1931],
  "with": [1204],
  "thank": [1103],
  "very": [568, 685],
  "much": [1102],
  "going": [1588],
  "well": [460],
  "never": [341, 568, 114],
  "better": [1614],
  "lately": [439, 479, 560],
  "actually": [1589, 2040, 367, 560],
  "which": [318, 396, 104],
  "attend": [286, 479, 110, 100],
  "attending": [286, 479, 110, 308, 110, 103],
  "enjoying": [2275, 279],
  "not": [734],
  "bad": [919],
  "lot": [352, 116],
  "of": [789],
  "people": [501, 387, 101],
  "that": [332],
  "today": [363, 1731, 121],
  "absolutely": [2358, 479, 560],
  "lovely": [352, 568, 560],
  "everything": [660, 395, 103],
  "haven": [1465, 110],
  "t": [116],
  "started": [636, 1551],
  "recently": [354, 527, 110, 116, 560],
  "where": [1954],
  "far": [515, 114],
  "my": [2111],
  "classes": [2463, 625, 285],
  "wish": [325, 313],
  "an": [267],
  "ugly": [2837, 560],
  "day": [1731, 121],
  "know": [554],
  "think": [1549],
  "may": [407, 121],
  "rain": [779],
  "the": [321],
  "middle": [543, 100, 100, 327],
  "summer": [3025],
  "shouldn": [313, 2593, 110],
  "would": [1056, 117, 498],
  "be": [345],
  "weird": [3016, 100],
  "yeah": [534, 97, 104],
  "especially": [1558, 367, 560],
  "since": [763, 110, 527],
  "ninety": [700, 341, 930],
  "degrees": [719, 1957, 101, 285],
  "outside": [259, 1477, 470, 101],
  "horrible": [334, 114, 335, 595],
  "if": [105, 102],
  "rained": [779, 609],
  "and": [653],
  "was": [972],
  "hot": [2640],
  "yes": [534, 115],
  "wasn": [972, 110],
  "every": [660],
  "me": [301],
  "too": [363, 111],
  "can": [447, 110],
  "wait": [929],
  "until": [1148, 108],
  "winter": [325, 110, 479, 114],
  "but": [323, 116],
  "sometimes": [468, 597, 115],
  "gets": [375, 1477],
  "cold": [1863],
  "d": [100],
  "rather": [421, 486],
  "than": [618],
  "doesn": [679, 110],
  "look": [352, 526],
  "nice": [700, 527],
  "re": [354],
  "later": [439, 479, 114],
  "raining": [779, 279],
  "wouldn": [1056, 117, 498, 110],
  "seem": [328, 1495],
  "considering": [394, 110, 763, 719, 335, 110, 103],
  "over": [111, 568, 114],
  "exactly": [689, 1589, 116, 560],
  "cool": [394, 111, 108],
  "off": [789, 102],
  "one": [440],
  "feel": [463, 949],
  "want": [312, 110, 116],
  "come": [1076],
  "soon": [1612],
  "enjoy": [2275],
  "mean": [602],
  "nicer": [700, 527, 114],
  "is": [492],
  "true": [1825, 117, 101],
  "hope": [334, 402],
  "degree": [719, 1957, 101, 101],
  "weather": [371, 286, 438, 114],
  "any": [590],
  "pointless": [2395, 327, 625],
  "down": [1162],
  "some": [468],
  "didn": [464, 110],
  "get": [375, 116],
  "though": [258, 1651],
  "deal": [719, 367],
  "such": [431, 305],
  "looks": [352, 526, 115],
  "does": [679],
  "why": [997],
  "love": [352, 568],
  "clears": [2172, 115],
  "air": [1635],
  "always": [863, 115],
  "smells": [2378, 115],
  "fresh": [1756, 285, 104],
  "after": [775, 479, 114],
  "rains": [779, 115],
  "night": [1170],
  "because": [582, 348, 101],
  "see": [924],
  "stars": [636, 115],
  "perfectly": [402, 114, 463, 577, 560],
  "isn": [492, 110],
  "seems": [328, 1495, 115],
  "hopefully": [334, 402, 835, 273, 121],
  "will": [1853],
  "clear": [2172],
  "sky": [115, 107, 121],
  "same": [422, 301],
  "way": [615],
  "when": [2382],
  "closer": [818, 328, 114],
  "don": [336, 110],
  "out": [579],
  "clean": [1054],
  "understand": [390, 719, 114, 3160, 100],
  "make": [407, 466],
  "smell": [2378],
  "cleaner": [1054, 264],
  "most": [3154],
  "at": [286],
  "more": [420, 354],
  "clearly": [2172, 560],
  "beach": [345, 1589, 104],
  "this": [258, 492],
  "weekend": [814, 466, 110, 100],
  "sounds": [360, 943, 115],
  "fun": [835, 110],
  "heard": [827, 100],
  "warm": [312, 114, 109],
  "perfect": [402, 114, 463, 577],
  "believe": [885, 381, 101],
  "california": [1916, 2127, 114, 700, 97],
  "unpredictable": [3029],
  "minute": [543, 1159, 479],
  "then": [1130],
  "next": [655, 116],
  "just": [3290, 306],
  "stay": [2524],
  "we": [371],
  "our": [2491],
  "activities": [1589, 355, 551, 355, 285],
  "planned": [1074, 341, 100],
  "ahead": [97, 438, 823],
  "time": [597],
  "things": [395, 2042],
  "easier": [2812, 264],
  "take": [445, 466],
  "trip": [1825, 2924],
  "forecast": [2127, 354, 447, 306],
  "says": [422, 121, 115],
  "on": [271],
  "ll": [273],
  "ruin": [522, 261],
  "badly": [919, 560],
  "constantly": [394, 110, 3160, 116, 560],
  "changing": [1256, 556, 110, 103],
  "change": [2260],
  "could": [394, 117, 498],
  "plan": [1074],
  "sooner": [1612, 264],
  "predictable": [2775, 922],
  "life": [1641],
  "sometime": [468, 597],
  "supposed": [431, 493, 111, 328, 100],
  "got": [344, 116],
  "stays": [2524, 115],
  "uncertain": [390, 527, 114, 2271],
  "impossible": [1094, 2966],
  "happen": [821],
  "different": [2076],
  "us": [348],
  "plans": [1074, 115],
  "hello": [2815, 111],
  "speak": [2181, 107],
  "alice": [367, 396, 101],
  "please": [1985],
  "she": [698],
  "trying": [1825, 121, 279],
  "call": [447, 273],
  "all": [367, 108],
  "sorry": [360, 114, 685],
  "cleaning": [1054, 279],
  "up": [692],
  "were": [371, 354],
  "calling": [447, 273, 279],
  "oh": [1152],
  "wanted": [312, 110, 1551],
  "hang": [274, 110, 103],
  "tomorrow": [363, 420, 114, 822],
  "sure": [839],
  "did": [464],
  "maybe": [407, 121, 345],
  "movie": [1396],
  "or": [283],
  "something": [468, 395, 103],
  "let": [875],
  "goodbye": [344, 111, 100, 2859, 101],
  "speaking": [2181, 1713, 110, 103],
  "answered": [2559, 264, 609],
  "phone": [1591],
  "had": [274, 100],
  "chores": [305, 283, 285],
  "reason": [354, 781, 271],
  "your": [266, 114],
  "mind": [543, 110, 100],
  "thinking": [395, 1713, 110, 103],
  "seeing": [328, 1240, 110, 103],
  "talk": [445, 108, 107],
  "available": [97, 2369, 1272, 922],
  "talking": [445, 108, 1713, 110, 103],
  "her": [438, 114],
  "called": [447, 273, 609],
  "hundred": [1965, 110, 100, 354, 100],
  "times": [597, 115],
  "busy": [2804],
  "apologize": [2421, 111, 352, 556, 122, 101],
  "need": [341, 609],
  "somewhere": [468, 1954],
  "special": [873, 101, 575, 367],
  "seen": [328, 282],
  "new": [855],
  "girl": [556, 114, 108],
  "describe": [719, 115, 1264, 345],
  "tall": [3143],
  "five": [537, 568],
  "feet": [463, 840],
  "even": [381, 282],
  "has": [274, 115],
  "light": [1932],
  "brown": [1104, 926, 110],
  "eyes": [2565, 285],
  "around": [2897],
  "yet": [1234],
  "tell": [479, 273],
  "kind": [1713, 110, 100],
  "short": [2537, 116],
  "height": [438, 1981],
  "probably": [530, 442, 98, 560],
  "first": [537, 114, 306],
  "thing": [395, 103],
  "noticed": [293, 355, 2348],
  "beautiful": [345, 97, 1375, 2439],
  "might": [543, 491],
  "bumped": [323, 109, 402, 100],
  "into": [261, 363],
  "before": [345, 2127, 354],
  "telling": [479, 273, 279],
  "met": [301, 116],
  "prettiest": [847, 105, 1200],
  "girls": [556, 114, 108, 115],
  "quite": [845, 2573],
  "say": [422, 121],
  "only": [271, 560],
  "facial": [515, 575, 367],
  "features": [463, 1938, 285],
  "who": [1221],
  "weren": [371, 354, 110],
  "yesterday": [534, 306, 264, 1731, 121],
  "feeling": [463, 949, 279],
  "wrong": [913, 866],
  "stomach": [1971, 305],
  "upset": [692, 328, 116],
  "anything": [590, 395, 103],
  "already": [367, 354, 823, 121],
  "took": [363, 526],
  "medicine": [1716, 575, 341],
  "missing": [543, 625, 279],
  "sick": [763, 605],
  "stomachache": [1971, 305, 1589, 438],
  "still": [306, 1272, 108],
  "under": [390, 719, 114],
  "earlier": [290, 114, 309, 264],
  "stayed": [2524, 609],
  "home": [1036],
  "bothering": [634, 486, 279],
  "little": [309, 434, 327],
  "store": [2932],
  "pepto": [402, 112, 363],
  "bismol": [769, 1118, 108],
  "hear": [827],
  "news": [1569],
  "promotion": [3033],
  "job": [729],
  "seriously": [328, 335, 947, 560],
  "am": [1005],
  "excited": [689, 575, 1551],
  "congratulations": [394, 110, 1957, 286, 117, 439, 812, 115],
  "happy": [2701],
  "deserved": [719, 328, 114, 568, 100],
  "told": [363, 498],
  "work": [1056, 114, 107],
  "week": [836],
  "truth": [1825, 117, 258],
  "serious": [328, 335, 947],
  "happened": [821, 609],
  "boss": [634, 625],
  "offered": [789, 463, 354, 100],
  "appreciate": [2421, 702, 575, 1543],
  "idea": [881],
  "real": [354, 367],
  "outfit": [579, 537, 116],
  "other": [1628],
  "from": [1756, 111, 109],
  "macy": [3041],
  "again": [1222],
  "these": [258, 285, 101],
  "shoes": [2887],
  "they": [258, 2565],
  "star": [636],
  "chuck": [2776, 605],
  "taylors": [445, 121, 352, 114, 115],
  "those": [1087, 328],
  "cost": [1243],
  "forty": [2127, 114, 930],
  "dollars": [2045, 115],
  "buy": [2288],
  "myself": [3095],
  "pair": [557, 465],
  "wearing": [371, 281, 279],
  "bought": [634, 2837, 104, 116],
  "couple": [394, 692, 327],
  "days": [1731, 121, 115],
  "ago": [1657],
  "santa": [422, 110, 445],
  "anita": [267, 287, 97],
  "mall": [407, 273],
  "chucks": [2776, 605, 115],
  "them": [258, 1495],
  "find": [537, 110, 100],
  "own": [926, 110],
  "cute": [676, 479],
  "brand": [1104, 653],
  "went": [371, 110, 116],
  "picked": [952, 605, 609],
  "found": [2127, 943],
  "spare": [873, 754],
  "drawing": [1236, 325, 110, 103],
  "painting": [557, 261, 355, 110, 103],
  "draw": [2665],
  "paint": [1583],
  "learn": [1723, 110],
  "learned": [1723, 341, 100],
  "back": [2338],
  "high": [489, 340],
  "art": [281, 116],
  "class": [2463, 625],
  "loved": [352, 568, 100],
  "talented": [445, 327, 110, 1551],
  "talent": [445, 327, 110, 116],
  "hidden": [489, 100, 719, 110],
  "kinds": [1713, 110, 100, 115],
  "liked": [1048, 100],
  "knew": [107, 855],
  "once": [271, 527],
  "while": [318, 1272, 101],
  "long": [352, 110, 103],
  "known": [430, 877],
  "sort": [360, 114, 116],
  "favorite": [515, 784, 335, 479],
  "hobbies": [334, 98, 769, 285],
  "often": [789, 479, 110],
  "taught": [445, 2837, 104, 116],
  "superbad": [431, 402, 114, 919],
  "funniest": [835, 110, 700, 1200],
  "ever": [457],
  "funny": [835, 110, 110, 121],
  "saw": [422, 119],
  "came": [447, 301],
  "theaters": [258, 290, 479, 114, 115],
  "laugh": [439, 2837, 104],
  "through": [258, 365, 2837, 104],
  "whole": [1221, 327],
  "brought": [1104, 1651, 116],
  "tears": [479, 281, 115],
  "mine": [543, 341],
  "dvd": [3189],
  "house": [334, 348, 101],
  "watch": [312, 116, 305],
  "honestly": [334, 341, 306, 560],
  "movies": [574, 285],
  "hilarious": [489, 439, 335, 947],
  "laughing": [439, 2837, 489, 110, 103],
  "couldn": [394, 117, 498, 110],
  "help": [1703],
  "either": [2261],
  "here": [438, 354],
  "course": [394, 467, 328],
  "best": [345, 306],
  "super": [431, 402, 114],
  "lying": [560, 279],
  "made": [407, 719],
  "line": [309, 341],
  "keep": [466, 1359],
  "throughout": [258, 365, 2837, 334, 117, 116],
  "hysterically": [104, 121, 306, 264, 396, 367, 560],
  "muscles": [538, 115, 665, 115],
  "hurt": [1965, 114, 116],
  "afterwards": [775, 479, 114, 312, 114, 100, 115],
  "felt": [463, 2417],
  "type": [930, 402],
  "music": [538, 763, 99],
  "listen": [2372],
  "listening": [2372, 279],
  "instance": [1504, 267, 527],
  "rock": [365, 605],
  "r&b": [114, 38, 98],
  "instruments": [2715, 301, 110, 1477],
  "use": [348, 101],
  "excellent": [2838, 273, 570],
  "various": [2369, 335, 947],
  "types": [930, 402, 115],
  "genres": [375, 110, 354, 115],
  "both": [634, 258],
  "interests": [261, 479, 354, 306, 115],
  "certain": [527, 114, 2271],
  "basketball": [2958, 1616],
  "game": [1039],
  "friday": [1756, 470, 322],
  "missed": [543, 625, 609],
  "won": [1056, 110],
  "played": [1133, 609],
  "should": [313, 2593],
  "exciting": [689, 575, 355, 110, 103],
  "score": [115, 394, 354],
  "man": [407, 110],
  "close": [818, 328],
  "able": [922],
  "unable": [390, 922],
  "intense": [261, 479, 110, 328],
  "ended": [282, 719, 100],
  "winning": [325, 110, 700, 110, 103],
  "team": [479, 1005],
  "victorious": [551, 577, 283, 1455],
  "free": [1756, 101, 101],
  "mad": [407, 100],
  "end": [578],
  "definitely": [719, 537, 700, 479, 560],
  "meaning": [602, 279],
  "ask": [781, 107],
  "hard": [721, 100],
  "final": [537, 1136, 108],
  "lost": [352, 306],
  "by": [2859],
  "three": [258, 1028],
  "points": [455, 261, 1477],
  "must": [538, 306],
  "gone": [344, 341],
  "friend": [1756, 105, 578],
  "nothing": [293, 395, 103],
  "another": [267, 1628],
  "none": [293, 341],
  "inviting": [261, 551, 355, 110, 103],
  "pass": [3188],
  "ideas": [881, 115],
  "as": [781],
  "theater": [258, 290, 479, 114],
  "planning": [1074, 700, 110, 103],
  "watching": [312, 116, 2264, 103],
  "catches": [447, 116, 305, 285],
  "eye": [2565, 101],
  "decided": [719, 575, 719, 100],
  "whether": [318, 840, 438, 114],
  "sucks": [431, 605, 115],
  "assignments": [781, 2240, 110, 301, 110, 1477],
  "english": [2818],
  "welcome": [2024, 1076],
  "glad": [1402, 100],
  "attended": [286, 479, 110, 719, 100],
  "ill": [1272, 108],
  "trouble": [1825, 259, 595],
  "return": [354, 2040, 114, 110],
  "favor": [515, 784, 114],
  "give": [556, 568],
  "mention": [301, 110, 812],
  "miss": [543, 625],
  "cousin": [394, 348, 261],
  "labor": [439, 634, 114],
  "baby": [442, 2859],
  "last": [439, 306],
  "anyone": [590, 440],
  "thought": [258, 1651, 116],
  "somebody": [468, 634, 3299],
  "pounds": [455, 943, 115],
  "ounces": [494, 527, 115],
  "god": [2545],
  "visit": [551, 763, 116],
  "debrah": [719, 1104, 97, 104],
  "letting": [2414, 279],
  "nobody": [293, 634, 3299],
  "wow": [1056, 119],
  "sad": [422, 100],
  "switch": [1662, 1460],
  "anyway": [2602],
  "odd": [111, 100, 100],
  "subject": [2542, 106, 101, 577],
  "stopping": [635, 493, 279],
  "alone": [2879],
  "instead": [1504, 290, 100],
  "bother": [634, 486],
  "random": [421, 110, 336, 109],
  "catch": [447, 116, 305],
  "coming": [394, 543, 110, 103],
  "tried": [1825, 105, 609],
  "working": [1056, 114, 1713, 110, 103],
  "regardless": [354, 548, 114, 100, 327, 625],
  "visited": [551, 763, 1551],
  "also": [367, 360],
  "basically": [442, 763, 447, 273, 121],
  "whatever": [318, 286, 457],
  "crazy": [2251],
  "hey": [438, 121],
  "jessica": [106, 285, 763, 447],
  "party": [557, 114, 930],
  "waiting": [929, 279],
  "invitation": [261, 551, 445, 812],
  "gave": [548, 568],
  "start": [1905],
  "starts": [636, 1477],
  "o": [111],
  "clock": [818, 605],
  "many": [407, 110, 121],
  "given": [556, 568, 110],
  "invites": [261, 551, 479, 115],
  "invite": [261, 551, 479],
  "saturday": [422, 2040, 114, 1731, 121],
  "morning": [420, 114, 700, 110, 103],
  "guessing": [1008, 763, 110, 103],
  "intend": [261, 479, 110, 100],
  "sound": [360, 943],
  "awesome": [97, 371, 468],
  "eight": [1240, 491],
  "invitations": [261, 551, 445, 812, 115],
  "gives": [556, 568, 115],
  "year": [837],
  "loads": [352, 823, 115],
  "p": [112],
  "hasn": [274, 115, 110],
  "throwing": [258, 365, 325, 110, 103],
  "realize": [354, 367, 105, 122, 101],
  "having": [274, 551, 110, 103],
  "doubt": [336, 117, 98, 116],
  "hate": [274, 479],
  "parties": [557, 114, 355, 285],
  "stand": [3160, 100],
  "guess": [1008, 115],
  "happening": [821, 279],
  "dinner": [308, 110, 341, 114],
  "family": [2487],
  "hold": [334, 498],
  "hoping": [334, 952, 110, 103],
  "try": [1825, 121],
  "rush": [522, 313],
  "nosey": [2791],
  "business": [323, 763, 341, 625],
  "harsh": [721, 313],
  "enjoyed": [1105, 534, 100],
  "conversing": [394, 110, 568, 114, 763, 110, 103],
  "fast": [1274],
  "done": [336, 341],
  "besides": [345, 763, 719, 115],
  "polite": [1238, 479],
  "being": [345, 279],
  "getting": [375, 434, 279],
  "ready": [354, 823, 121],
  "care": [447, 354],
  "worry": [1056, 114, 685],
  "eat": [290, 116],
  "bye": [2859, 101],
  "set": [328, 116],
  "live": [309, 568],
  "pasadena": [1999, 719, 1136],
  "northern": [293, 114, 486, 110],
  "southern": [360, 117, 486, 110],
  "city": [575, 930],
  "los": [352, 115],
  "angeles": [1941, 327, 115],
  "million": [2318, 1937],
  "car": [447, 114],
  "honda": [334, 110, 1731],
  "old": [1529],
  "wash": [2266],
  "oil": [111, 1272],
  "mechanic": [301, 1256, 396],
  "changes": [2260, 115],
  "twice": [746, 396, 101],
  "girlfriend": [556, 114, 1150, 335, 578],
  "rich": [2690],
  "enough": [2836],
  "guys": [2012, 115],
  "money": [420, 341, 121],
  "cars": [447, 114, 115],
  "neither": [341, 287, 438, 114],
  "jokes": [586, 466, 115],
  "walk": [1478],
  "dog": [985],
  "poodle": [455, 111, 100, 327],
  "poodles": [455, 111, 100, 327, 115],
  "bark": [442, 114, 107],
  "shut": [313, 117, 116],
  "mom": [1493],
  "likes": [1048, 115],
  "watchdogs": [312, 116, 305, 336, 2042],
  "borrow": [634, 114, 822],
  "lunch": [658, 110, 305],
  "wallet": [312, 273, 840],
  "empty": [2533],
  "dollar": [2045],
  "broke": [1104, 526, 101],
  "friends": [1756, 105, 578, 115],
  "lend": [327, 110, 100],
  "pay": [557, 121],
  "month": [420, 110, 258],
  "almost": [367, 3154],
  "drowned": [1781, 877, 609],
  "lifeguard": [1641, 661, 1869],
  "dive": [308, 568],
  "water": [312, 479, 114],
  "he": [438],
  "swam": [1662, 1005],
  "turned": [2040, 114, 341, 100],
  "married": [407, 114, 2139],
  "divorced": [308, 784, 114, 2348],
  "two": [2037],
  "years": [837, 115],
  "wife": [325, 463],
  "left": [2866],
  "leave": [327, 97, 568],
  "said": [422, 470],
  "anymore": [590, 420, 354],
  "terrible": [479, 114, 335, 595],
  "fell": [463, 273],
  "bored": [634, 354, 100],
  "tv": [808],
  "interesting": [261, 479, 354, 306, 279],
  "show": [313, 926],
  "joking": [586, 1713, 110, 103],
  "watched": [312, 116, 305, 609],
  "together": [2432],
  "living": [309, 551, 110, 103],
  "agree": [97, 1957, 101, 101],
  "small": [115, 407, 273],
  "rose": [365, 328],
  "parade": [557, 421, 719],
  "houses": [334, 348, 285],
  "wonderful": [1056, 110, 719, 114, 2439],
  "restaurants": [354, 2192, 467, 267, 1477],
  "schools": [817, 115],
  "mountains": [420, 390, 2271, 115],
  "friendly": [1756, 105, 578, 560],
  "mattress": [407, 434, 354, 625],
  "matter": [407, 434, 264],
  "comfortable": [749, 2127, 114, 445, 595],
  "toss": [363, 625],
  "turn": [2040, 114, 110],
  "stop": [2936],
  "drinking": [905, 110, 1713, 110, 103],
  "coffee": [394, 563, 101, 101],
  "marks": [407, 114, 107, 115],
  "arms": [281, 109, 115],
  "bites": [769, 479, 115],
  "cat": [447, 116],
  "bite": [769, 479],
  "bedbugs": [1671, 323, 2042],
  "bit": [769, 116],
  "laptop": [2424, 112],
  "slow": [2375],
  "computer": [2660, 479, 114],
  "shop": [3227],
  "throw": [2517],
  "window": [325, 110, 1755],
  "hit": [489, 116],
  "someone": [2608],
  "head": [438, 823],
  "pizza": [2365],
  "everybody": [660, 634, 3299],
  "loves": [352, 568, 115],
  "variety": [2369, 335, 840, 121],
  "pepperoni": [2278, 264, 271, 105],
  "cheese": [2926, 101],
  "salad": [422, 439, 100],
  "save": [422, 568],
  "expensive": [689, 402, 110, 763, 568],
  "payment": [557, 121, 301, 110, 116],
  "thirty": [1910, 930],
  "thousand": [258, 259, 422, 110, 100],
  "forever": [2127, 354, 568, 114],
  "penny": [402, 110, 110, 121],
  "seven": [328, 568, 110],
  "pennies": [402, 110, 700, 285],
  "ocean": [2020, 290, 110],
  "goes": [344, 285],
  "deep": [719, 1359],
  "miles": [543, 327, 115],
  "fish": [2582],
  "bottom": [634, 434, 111, 109],
  "top": [363, 112],
  "warned": [312, 114, 341, 100],
  "boyfriend": [3145, 1756, 105, 578],
  "birthday": [769, 114, 258, 1731, 121],
  "spend": [873, 578],
  "herself": [438, 2341],
  "ring": [335, 110, 103],
  "las": [439, 115],
  "vegas": [568, 548, 115],
  "gambling": [548, 809, 309, 110, 103],
  "him": [1144],
  "animals": [2485, 115],
  "each": [1972],
  "else": [1368],
  "food": [2127, 111, 100],
  "funny-looking": [835, 110, 110, 121, 45, 352, 526, 279],
  "ha": [274],
  "wear": [371, 281],
  "clothes": [818, 258, 285],
  "dirty": [1908],
  "helped": [1020, 402, 100],
  "bathroom": [442, 258, 365, 111, 109],
  "easy": [1088, 121],
  "sink": [763, 110, 107],
  "tub": [2040, 98],
  "counter": [394, 390, 479, 114],
  "toilet": [363, 1272, 840],
  "finish": [537, 700, 313],
  "wasting": [312, 306, 279],
  "sitting": [763, 434, 279],
  "mouth": [420, 117, 258],
  "open": [111, 402, 110],
  "cares": [447, 354, 115],
  "volume": [784, 658, 301],
  "meant": [602, 116],
  "write": [3014, 101],
  "letter": [2414, 264],
  "grandma": [1957, 653, 407],
  "put": [572, 116],
  "envelope": [2221],
  "sealed": [328, 367, 609],
  "stamp": [1769, 112],
  "stamps": [1769, 2083],
  "kitchen": [1713, 116, 305, 282],
  "drawer": [1236, 371, 114],
  "mail": [2971],
  "e-mail": [101, 45, 2971],
  "yawning": [121, 97, 877, 279],
  "sleepy": [2402, 121],
  "bed": [1671],
  "record": [354, 394, 114, 100],
  "tape": [445, 402],
  "recorder": [354, 394, 114, 719, 114],
  "broken": [1104, 526, 282],
  "rerun": [354, 522, 110],
  "original": [283, 105, 556, 1136, 108],
  "asleep": [781, 327, 1359],
  "commercials": [394, 1653, 264, 575, 367, 115],
  "ends": [578, 115],
  "zzz": [1447, 122],
  "sunday": [431, 110, 1731, 121],
  "means": [602, 115],
  "forgot": [2127, 114, 344, 116],
  "church": [2819, 305],
  "coat": [394, 286],
  "tie": [355, 101],
  "respect": [354, 873, 101, 577],
  "others": [1628, 115],
  "forgive": [2127, 114, 556, 568],
  "feed": [463, 609],
  "meowing": [301, 926, 279],
  "hungry": [1965, 110, 1957, 121],
  "homework": [1036, 1056, 114, 107],
  "cats": [447, 1477],
  "themselves": [258, 1495, 328, 108, 568, 115],
  "rid": [2881],
  "shaving": [313, 97, 551, 110, 103],
  "cut": [676, 116],
  "blade": [1199, 719],
  "blades": [1199, 719, 115],
  "electric": [949, 101, 577, 335, 99],
  "shaver": [313, 97, 568, 114],
  "noise": [293, 492, 101],
  "shave": [313, 97, 568],
  "grow": [1957, 926],
  "beard": [345, 1869],
  "stuff": [968, 563],
  "sticks": [306, 1006, 115],
  "hmm": [104, 1653],
  "cream": [1835, 1005],
  "face": [515, 527],
  "lick": [309, 605],
  "excuse": [689, 676, 328],
  "reading": [354, 823, 279],
  "paper": [557, 402, 114],
  "asked": [781, 466, 100],
  "pick": [952, 605],
  "rude": [522, 719],
  "world": [1056, 114, 498],
  "needs": [341, 609, 115],
  "percent": [402, 114, 527, 110, 116],
  "puppy": [572, 493, 121],
  "costs": [1243, 115],
  "puppies": [572, 493, 105, 285],
  "shots": [550, 1477],
  "eats": [290, 1477],
  "plate": [387, 1543],
  "vegetables": [568, 375, 445, 595, 115],
  "kittens": [1713, 434, 282, 115],
  "away": [2205],
  "black": [1199, 605],
  "blacky": [1199, 605, 121],
  "parents": [557, 354, 110, 1477],
  "trust": [1825, 348, 116],
  "heaven": [438, 97, 568, 110],
  "knows": [554, 115],
  "happens": [821, 115],
  "die": [2595],
  "unhappy": [390, 2701],
  "hell": [2815],
  "husband": [1965, 115, 442, 110, 100],
  "died": [308, 609],
  "months": [420, 110, 258, 115],
  "his": [489, 115],
  "cell": [527, 273],
  "buried": [323, 2139],
  "battery": [442, 434, 264, 121],
  "dies": [308, 285],
  "thirteenth": [1910, 479, 282, 258],
  "unlucky": [390, 1931, 121],
  "hotel": [2899, 108],
  "mistake": [543, 2192, 466],
  "floor": [2864],
  "stole": [635, 327],
  "lesson": [327, 625, 271],
  "prove": [530, 568],
  "restaurant": [354, 2192, 467, 802],
  "mcdonald": [2700, 336, 1136, 498],
  "reservation": [354, 328, 114, 2369, 812],
  "hassle": [274, 625, 327],
  "father": [515, 486],
  "mother": [420, 486],
  "angry": [267, 1957, 121],
  "drop": [1781, 112],
  "moved": [420, 568, 100],
  "apartment": [2421, 281, 116, 301, 110, 116],
  "begin": [345, 556, 110],
  "fruit": [1756, 117, 287],
  "ripe": [335, 402],
  "thrift": [258, 335, 102, 116],
  "price": [2152],
  "used": [348, 609],
  "born": [634, 114, 110],
  "cents": [527, 110, 1477],
  "complain": [2895],
  "button": [1063, 271],
  "shirt": [2074, 116],
  "lose": [352, 328],
  "pant": [557, 110, 116],
  "cuffs": [676, 563, 115],
  "shirts": [2074, 1477],
  "extra": [3193, 97],
  "sew": [328, 119],
  "drink": [905, 110, 107],
  "chocolate": [305, 2020, 111, 439, 479],
  "looked": [352, 526, 609],
  "mirror": [543, 114, 365, 114],
  "fat": [515, 116],
  "laundry": [439, 943, 685],
  "washed": [2266, 609],
  "sheets": [3296, 115],
  "towels": [2611, 115],
  "pillowcases": [3136, 447, 328, 115],
  "pillows": [3136, 115],
  "dry": [100, 685],
  "dryer": [100, 685, 264],
  "dried": [905, 609],
  "folded": [2127, 498, 609],
  "beds": [1671, 115],
  "radio": [2998],
  "mostly": [3154, 560],
  "current": [676, 114, 354, 110, 116],
  "events": [381, 282, 1477],
  "tax": [1964],
  "cuts": [676, 1477],
  "fridge": [1756, 470, 375],
  "looking": [352, 526, 279],
  "market": [407, 114, 1760],
  "lots": [352, 1477],
  "oranges": [283, 1941, 115],
  "apples": [2421, 2656],
  "tasty": [2157, 121],
  "dogs": [336, 2042],
  "candy": [447, 110, 3299],
  "bars": [442, 114, 115],
  "sandwich": [422, 110, 100, 325, 305],
  "ham": [1528],
  "bread": [1104, 290, 100],
  "cabinet": [447, 769, 341, 116],
  "mustard": [538, 636, 100],
  "potato": [455, 445, 363],
  "chips": [305, 2924, 115],
  "pickle": [952, 605, 327],
  "bath": [442, 258],
  "young": [2856, 103],
  "lady": [439, 3299],
  "smelled": [2378, 609],
  "perfume": [402, 114, 835, 301],
  "screen": [3141, 282],
  "drive": [905, 568],
  "crashed": [2374, 609],
  "hp": [104, 112],
  "files": [537, 327, 115],
  "smart": [115, 407, 114, 116],
  "plus": [387, 348],
  "installation": [1504, 367, 439, 812],
  "remove": [354, 420, 568],
  "replace": [354, 387, 1589, 101],
  "screws": [3141, 119, 115],
  "paying": [557, 121, 279],
  "crashes": [2374, 285],
  "email": [1495, 97, 1272],
  "address": [2612, 354, 625],
  "bluedog123": [1398, 609, 111, 103, 738, 51],
  "incomplete": [261, 749, 387, 840, 101],
  "mailing": [2971, 279],
  "cherry": [305, 264, 685],
  "ca": [447],
  "correct": [394, 114, 354, 577],
  "street": [1844],
  "state": [306, 1543],
  "zip": [122, 2924],
  "code": [394, 719],
  "bluedog123@yahoo": [1398, 609, 111, 103, 738, 51, 64, 121, 97, 334, 111],
  "com": [749],
  "nap": [2579],
  "unplug": [390, 387, 2837],
  "wake": [312, 466],
  "hour": [334, 467],
  "sleep": [2402],
  "awake": [97, 312, 466],
  "nose": [1157],
  "cooking": [394, 526, 279],
  "dream": [100, 354, 1005],
  "tired": [355, 354, 100],
  "funeral": [835, 341, 421, 108],
  "dad": [1731, 100],
  "son": [360, 110],
  "speech": [873, 101, 101, 305],
  "minutes": [543, 1159, 479, 115],
  "yikes": [121, 105, 466, 115],
  "blow": [98, 1449],
  "plane": [1074, 101],
  "loud": [352, 117, 100],
  "word": [1056, 114, 100],
  "elephant": [949, 1359, 274, 110, 116],
  "deaf": [719, 775],
  "twenty-five": [746, 282, 930, 45, 537, 568],
  "few": [463, 119],
  "lonely": [352, 341, 560],
  "share": [313, 754],
  "cheat": [1840, 116],
  "men": [301, 110],
  "book": [634, 526],
  "cheater": [1840, 479, 114],
  "poke": [455, 466],
  "woman": [1056, 407, 110],
  "chop": [305, 111, 112],
  "toes": [363, 285],
  "honey": [334, 341, 121],
  "swear": [1662, 290, 114],
  "meet": [301, 840],
  "jerks": [106, 2922, 115],
  "full": [835, 273],
  "everywhere": [660, 1954],
  "yell": [534, 273],
  "yelling": [534, 273, 279],
  "form": [2127, 114, 109],
  "problems": [798, 115],
  "mi": [543],
  "stands": [3160, 100, 115],
  "initial": [261, 287, 105, 367],
  "mm/dd/yy": [1653, 47, 100, 100, 47, 121, 121],
  "month/day/year": [420, 110, 258, 47, 1731, 121, 47, 837],
  "numbers": [1218, 1069],
  "example": [689, 1005, 387, 101],
  "birth": [769, 114, 258],
  "date": [1731, 479],
  "january": [1915, 1159, 2896],
  "simple": [763, 109, 387, 101],
  "print": [1241, 110, 116],
  "fill": [537, 273],
  "bubbles": [323, 98, 595, 115],
  "completely": [749, 387, 840, 949, 121],
  "animal": [2485],
  "shelter": [313, 949, 479, 114],
  "showed": [313, 926, 609],
  "bet": [345, 116],
  "drag": [1236, 103],
  "wonder": [1056, 110, 719, 114],
  "name": [1136, 301],
  "woke": [1056, 466],
  "gray": [1957, 322],
  "wet": [371, 116],
  "shopping": [550, 493, 279],
  "umbrella": [117, 809, 354, 273, 97],
  "noon": [293, 271],
  "hotter": [334, 434, 264],
  "dying": [3299, 279],
  "heat": [2683],
  "conditioner": [394, 110, 308, 812, 264],
  "repairman": [354, 557, 465, 407, 110],
  "comes": [1076, 115],
  "snow": [115, 747],
  "snowman": [115, 747, 407, 110],
  "carrot": [447, 114, 365, 116],
  "bank": [442, 110, 107],
  "withdraw": [1204, 2665],
  "atm": [286, 109],
  "automatic": [97, 117, 363, 407, 355, 99],
  "teller": [479, 273, 264],
  "machine": [407, 2264, 101],
  "insert": [261, 328, 114, 116],
  "debit": [719, 769, 116],
  "card": [447, 114, 100],
  "blue": [1824],
  "bin": [769, 110],
  "front": [2056, 116],
  "recycle": [354, 1984, 665],
  "truck": [1825, 117, 605],
  "usually": [348, 117, 367, 560],
  "tuesday": [2040, 285, 1731, 121],
  "late": [439, 479],
  "forget": [2127, 114, 375, 116],
  "remember": [1925, 264],
  "nation": [1136, 812],
  "switching": [1662, 1460, 279],
  "digital": [308, 556, 445, 108],
  "converter": [394, 110, 568, 114, 479, 114],
  "inch": [261, 305],
  "channels": [2498, 115],
  "six": [763, 120],
  "korean": [107, 283, 290, 110],
  "pilot": [952, 352, 116],
  "canada": [447, 1136, 1731],
  "flew": [102, 327, 119],
  "u": [117],
  "fighter": [537, 340, 479, 114],
  "jets": [106, 840, 115],
  "followed": [2562, 609],
  "landed": [439, 110, 719, 100],
  "highway": [489, 340, 615],
  "crash": [2374],
  "walked": [1019, 466, 100],
  "cops": [394, 2083],
  "sucked": [431, 605, 609],
  "jet": [106, 840],
  "shoot": [2953, 116],
  "poor": [455, 283],
  "guy": [2012],
  "police": [2013],
  "finding": [537, 110, 308, 110, 103],
  "robber": [3144, 345, 114],
  "reporting": [354, 455, 114, 355, 110, 103],
  "robbery": [3144, 345, 685],
  "hair": [274, 465],
  "race": [421, 527],
  "racist": [421, 575, 306],
  "identify": [470, 282, 355, 102, 121],
  "their": [258, 1240, 114],
  "male": [407, 327],
  "female": [463, 407, 327],
  "sexist": [328, 120, 492, 116],
  "wipe": [325, 402],
  "sleeve": [1518, 381, 101],
  "tissue": [355, 625, 117, 101],
  "sleeves": [1518, 381, 285],
  "tissues": [355, 625, 117, 285],
  "age": [1887],
  "daddy": [1731, 100, 3299],
  "boy": [3145],
  "mommy": [420, 1653, 121],
  "worried": [1056, 114, 2139],
  "marriage": [407, 114, 335, 1887],
  "responsibility": [354, 873, 271, 763, 769, 309, 930],
  "children": [305, 1272, 100, 354, 110],
  "except": [2838, 112, 116],
  "afford": [775, 2127, 114, 100],
  "artists": [3244, 115],
  "jar": [1915, 114],
  "pencils": [402, 110, 575, 108, 115],
  "artist": [3244],
  "differently": [2076, 560],
  "picasso": [952, 447, 625, 111],
  "painted": [557, 261, 1551],
  "famous": [515, 420, 348],
  "lessons": [327, 625, 271, 115],
  "drew": [100, 354, 119],
  "paintings": [557, 261, 355, 110, 2042],
  "third": [1910, 100],
  "grade": [1957, 823, 101],
  "worth": [1056, 114, 258],
  "millions": [2318, 1937, 115],
  "point": [2395],
  "aren": [281, 282],
  "patient": [557, 355, 570],
  "along": [367, 866],
  "beer": [345, 264],
  "powerful": [455, 371, 114, 2439],
  "drug": [1913, 103],
  "cigarettes": [575, 548, 354, 434, 285],
  "prefer": [702, 463, 114],
  "offer": [789, 463, 114],
  "tough": [363, 2837, 104],
  "taste": [2157, 101],
  "pants": [557, 110, 1477],
  "hole": [334, 327],
  "pocket": [455, 605, 840],
  "carry": [447, 114, 685],
  "pens": [402, 110, 115],
  "pen": [402, 110],
  "onto": [271, 363],
  "shoe": [550, 101],
  "lucky": [1931, 121],
  "sharp": [313, 281, 112],
  "knife": [107, 700, 463],
  "carries": [447, 114, 335, 285],
  "criminals": [1264, 543, 1136, 108, 115],
  "fix": [537, 120],
  "iron-on": [465, 271, 45, 271],
  "patch": [557, 116, 305],
  "glue": [103, 658, 101],
  "iron": [465, 271],
  "melts": [301, 2417, 115],
  "sewing": [328, 325, 110, 103],
  "ten": [479, 110],
  "washings": [2266, 261, 2042],
  "washes": [2266, 285],
  "ear": [290, 114],
  "makes": [407, 466, 115],
  "ones": [271, 285],
  "language": [439, 110, 661, 1887],
  "joke": [586, 466],
  "women": [1056, 301, 110],
  "languages": [439, 110, 661, 1887, 115],
  "speaks": [2181, 107, 115],
  "learning": [1723, 700, 110, 103],
  "spanish": [873, 267, 492, 104],
  "teach": [479, 1589, 104],
  "ahora": [97, 334, 421],
  "april": [2421, 335, 108],
  "anniversary": [267, 700, 568, 114, 422, 685],
  "earth": [290, 114, 258],
  "yearly": [837, 560],
  "reminder": [354, 543, 110, 719, 114],
  "planet": [1074, 840],
  "reuse": [354, 348, 101],
  "green": [1957, 101, 282],
  "using": [348, 279],
  "plastic": [387, 781, 355, 99],
  "bags": [442, 2042],
  "shorter": [2537, 479, 114],
  "showers": [313, 926, 1069],
  "waste": [312, 306, 101],
  "shower": [313, 926, 264],
  "poetry": [455, 840, 685],
  "poems": [455, 1495, 115],
  "rhyme": [114, 104, 121, 301],
  "buckle": [323, 605, 327],
  "shakespeare": [313, 97, 466, 2181, 354],
  "poet": [455, 840],
  "songs": [360, 110, 2042],
  "without": [1204, 579],
  "suck": [431, 605],
  "average": [97, 568, 421, 375],
  "iq": [105, 113],
  "test": [479, 306],
  "b": [98],
  "ridiculous": [335, 308, 676, 352, 348],
  "super-smart": [431, 402, 114, 45, 115, 407, 114, 116],
  "understands": [390, 719, 114, 3160, 100, 115],
  "saying": [422, 121, 279],
  "whenever": [2382, 457],
  "lead": [327, 823],
  "story": [2757],
  "actress": [1589, 1825, 2345],
  "court": [394, 467, 116],
  "driving": [905, 551, 110, 103],
  "license": [309, 527, 110, 328],
  "second": [328, 394, 110, 100],
  "actor": [1589, 363, 114],
  "daughter": [1731, 2837, 104, 479, 114],
  "bull": [323, 273],
  "chased": [305, 781, 609],
  "supermarket": [431, 402, 114, 407, 114, 1760],
  "octo-mom": [2607, 45, 1493],
  "hire": [489, 354],
  "nanny": [1136, 110, 110, 121],
  "infants": [261, 515, 110, 1477],
  "death": [719, 286, 104],
  "avoid": [97, 784, 470],
  "cremated": [1835, 407, 1551],
  "ashes": [781, 438, 115],
  "shaken": [313, 97, 466, 110],
  "coffin": [394, 563, 261],
  "takes": [445, 466, 115],
  "space": [873, 1589, 101],
  "cemetery": [3158, 479, 685],
  "seldom": [328, 498, 111, 109],
  "dead": [719, 823],
  "figure": [537, 661, 354],
  "kids": [1713, 100, 115],
  "wiped": [325, 402, 100],
  "mud": [538, 100],
  "carpet": [447, 114, 2314],
  "vacuum": [2540, 109],
  "till": [355, 273],
  "dries": [905, 285],
  "careful": [447, 354, 2439],
  "raised": [421, 492, 609],
  "flag": [1998, 103],
  "flags": [1998, 2042],
  "stripes": [306, 335, 402, 115],
  "war": [312, 114],
  "carrying": [447, 114, 685, 279],
  "watered": [312, 479, 354, 100],
  "plants": [1074, 1477],
  "vacuumed": [2540, 301, 100],
  "entire": [282, 355, 354],
  "distance": [308, 3160, 527],
  "service": [328, 114, 551, 527],
  "calls": [447, 273, 115],
  "dial": [308, 367],
  "college": [2817],
  "teachers": [479, 1589, 438, 114, 115],
  "classmates": [2463, 625, 407, 479, 115],
  "check": [2438],
  "pockets": [455, 605, 840, 115],
  "checked": [2438, 609],
  "desk": [719, 115, 107],
  "gravity": [1957, 97, 551, 930],
  "important": [1094, 455, 114, 445, 110, 116],
  "force": [2127, 114, 527],
  "pulls": [572, 273, 115],
  "pour": [455, 467],
  "glass": [1402, 625],
  "float": [1783, 286],
  "balloon": [1616, 294, 110],
  "read": [354, 823],
  "doctor": [1296],
  "prescription": [702, 115, 1264, 112, 812],
  "glasses": [1402, 625, 285],
  "appointment": [2421, 2395, 301, 110, 116],
  "yellow": [534, 1805],
  "pages": [557, 375, 115],
  "number": [2842],
  "case": [447, 328],
  "hearing": [827, 279],
  "notebook": [293, 479, 634, 526],
  "calculator": [447, 108, 676, 439, 363, 114],
  "teacher": [479, 1589, 438, 114],
  "permit": [402, 114, 543, 116],
  "calculators": [447, 108, 676, 439, 363, 114, 115],
  "dictionary": [308, 577, 1937, 2896],
  "classroom": [2463, 625, 365, 111, 109],
  "magazine": [407, 548, 122, 3009],
  "subscribed": [2542, 115, 1264, 1671],
  "political": [1238, 355, 447, 108],
  "cartoons": [447, 114, 363, 271, 115],
  "photos": [907, 111, 363, 115],
  "sale": [2918],
  "film": [537, 108, 109],
  "reviews": [354, 551, 101, 119, 115],
  "section": [328, 577, 1937],
  "subscription": [2542, 115, 1264, 112, 812],
  "canceled": [447, 110, 527, 327, 100],
  "magazines": [407, 548, 122, 1933],
  "ink": [1696],
  "shake": [313, 97, 466],
  "shook": [2953, 107],
  "writing": [3014, 279],
  "rules": [522, 327, 115],
  "graduate": [1957, 823, 117, 1543],
  "joining": [586, 261, 279],
  "army": [281, 2111],
  "kidding": [1713, 100, 308, 110, 103],
  "killed": [1713, 273, 609],
  "major": [407, 586, 114],
  "teaching": [479, 1589, 489, 110, 103],
  "totally": [363, 3143, 121],
  "parking": [557, 114, 1713, 110, 103],
  "drove": [1781, 568],
  "half": [274, 1150],
  "spot": [873, 111, 116],
  "yelled": [534, 273, 609],
  "huge": [1965, 375],
  "library": [309, 1104, 2896],
  "rooms": [365, 111, 109, 115],
  "books": [634, 526, 115],
  "thieves": [2820, 285],
  "belongings": [345, 352, 110, 556, 110, 2042],
  "backpack": [2338, 557, 605],
  "ipod": [2924, 111, 100],
  "safe": [422, 463],
  "math": [407, 258],
  "add": [2612],
  "taking": [445, 1713, 110, 103],
  "stupid": [306, 692, 470],
  "pray": [2381, 121],
  "occasionally": [2020, 447, 763, 271, 367, 560],
  "prayers": [2381, 534, 114, 115],
  "passed": [3188, 609],
  "tests": [479, 306, 115],
  "finally": [537, 1136, 273, 121],
  "driver": [905, 568, 114],
  "ran": [421, 110],
  "students": [968, 719, 110, 1477],
  "instantly": [1504, 802, 560],
  "hospital": [2465],
  "pushed": [572, 313, 609],
  "hood": [334, 111, 100],
  "gently": [375, 110, 116, 560],
  "placed": [387, 1589, 609],
  "fire": [2468],
  "department": [719, 557, 114, 116, 301, 110, 116],
  "nearby": [341, 281, 2859],
  "turning": [2040, 114, 700, 110, 103],
  "himself": [1144, 1552],
  "riding": [335, 308, 110, 103],
  "bus": [1049],
  "seats": [1818, 115],
  "windows": [325, 110, 1755, 115],
  "bring": [1104, 279],
  "wipes": [325, 402, 115],
  "seat": [1818],
  "strange": [306, 421, 110, 375],
  "everyone": [660, 440],
  "faster": [1274, 264],
  "buses": [323, 328, 115],
  "run": [522, 110],
  "hours": [334, 467, 115],
  "four": [2127, 467],
  "crowded": [1899, 119, 719, 100],
  "aisle": [97, 492, 327],
  "unsafe": [390, 422, 463],
  "rob": [3144],
  "tires": [355, 354, 115],
  "student": [968, 719, 110, 116],
  "eleven": [949, 381, 282],
  "person": [402, 114, 360, 110],
  "fair": [515, 465],
  "ticket": [355, 605, 840],
  "crossing": [2116, 279],
  "crosswalk": [3187],
  "red": [354, 100],
  "hand": [274, 110, 100],
  "blinking": [98, 309, 110, 1713, 110, 103],
  "cross": [2116],
  "white": [318, 2573],
  "sign": [2240, 110],
  "speed": [873, 101, 609],
  "limit": [309, 543, 116],
  "cop": [394, 112],
  "stops": [635, 2083],
  "fastest": [1274, 1200],
  "flat": [1998, 116],
  "hurry": [1965, 114, 685],
  "fault": [515, 117, 2417],
  "accident": [1589, 575, 719, 110, 116],
  "accidents": [1589, 575, 719, 110, 1477],
  "drunks": [1913, 110, 107, 115],
  "caused": [447, 348, 609],
  "ride": [335, 719],
  "cadillac": [447, 308, 273, 1589],
  "luxury": [658, 120, 467, 121],
  "keys": [466, 121, 115],
  "camera": [447, 301, 421],
  "longer": [352, 110, 375, 114],
  "explode": [689, 387, 111, 719],
  "bumps": [323, 109, 2083],
  "hamburger": [274, 809, 467, 375, 114],
  "exit": [689, 287],
  "park": [557, 114, 107],
  "parked": [557, 114, 466, 100],
  "tree": [1825, 101, 101],
  "steal": [1830, 108],
  "towed": [363, 371, 100],
  "traffic": [1825, 775, 537, 99],
  "worse": [1056, 114, 328],
  "complaining": [2895, 279],
  "between": [345, 746, 101, 282],
  "honk": [334, 110, 107],
  "horn": [334, 114, 110],
  "bucket": [323, 605, 840],
  "rinse": [335, 110, 328],
  "scrub": [115, 3005, 98],
  "sponge": [873, 271, 375],
  "soap": [360, 2421],
  "towel": [2611],
  "windy": [325, 110, 3299],
  "flying": [102, 560, 279],
  "wind": [325, 110, 100],
  "dangerous": [1731, 110, 375, 365, 348],
  "drivers": [905, 568, 114, 115],
  "trucks": [1825, 117, 605, 115],
  "blows": [98, 1449, 115],
  "trees": [1825, 101, 285],
  "damage": [1731, 407, 375],
  "birds": [769, 114, 100, 115],
  "pull": [572, 273],
  "kill": [1713, 273],
  "stone": [306, 440],
  "order": [283, 719, 114],
  "yours": [266, 114, 115],
  "left-turn": [2866, 45, 2040, 114, 110],
  "arrow": [281, 822],
  "lane": [439, 341],
  "straight": [306, 421, 1981],
  "u-turn": [117, 45, 2040, 114, 110],
  "quicker": [845, 396, 466, 114],
  "cheap": [1840, 112],
  "reliable": [354, 309, 922],
  "low": [1449],
  "mileage": [543, 327, 1887],
  "owned": [926, 341, 100],
  "anywhere": [590, 1954],
  "saving": [422, 551, 110, 103],
  "afternoon": [775, 479, 114, 293, 271],
  "officer": [789, 537, 527, 114],
  "registration": [354, 556, 306, 421, 812],
  "pulled": [572, 273, 609],
  "sudden": [431, 100, 719, 110],
  "siren": [763, 354, 110],
  "rolled": [365, 273, 609],
  "stopped": [635, 493, 609],
  "slowed": [115, 352, 371, 100],
  "attitude": [286, 355, 2040, 719],
  "downtown": [1162, 2997],
  "speeding": [873, 101, 609, 279],
  "jaywalking": [1915, 121, 1019, 1713, 110, 103],
  "entered": [282, 479, 354, 100],
  "fight": [3198],
  "witness": [325, 116, 341, 625],
  "near": [341, 281],
  "usc": [348, 99],
  "killing": [1713, 273, 279],
  "passenger": [3188, 282, 375, 114],
  "injured": [261, 3290, 354, 100],
  "continued": [394, 110, 355, 1159, 609],
  "its": [287, 115],
  "jail": [1915, 1272],
  "dent": [719, 110, 116],
  "cart": [447, 114, 116],
  "carts": [447, 114, 1477],
  "metal": [301, 445, 108],
  "uses": [348, 285],
  "saved": [422, 568, 100],
  "titanic": [355, 445, 700, 99],
  "twelve": [746, 949, 568],
  "cry": [99, 685],
  "play": [1133],
  "cards": [447, 114, 100, 115],
  "games": [1039, 115],
  "poker": [455, 466, 114],
  "tens": [479, 110, 115],
  "player": [1133, 264],
  "players": [1133, 1069],
  "licks": [309, 605, 115],
  "lips": [309, 2083],
  "wins": [325, 110, 115],
  "nope": [293, 402],
  "drives": [905, 568, 115],
  "thinks": [1549, 115],
  "cheating": [1840, 355, 110, 103],
  "quietly": [845, 105, 840, 560],
  "room": [365, 111, 109],
  "remind": [354, 543, 110, 100],
  "radios": [2998, 115],
  "neighbors": [2058, 634, 114, 115],
  "move": [420, 568],
  "win": [325, 110],
  "lotto": [352, 434, 111],
  "chances": [1256, 527, 115],
  "quit": [845, 287],
  "playing": [1133, 279],
  "baseball": [442, 328, 1616],
  "rainstorm": [779, 903, 109],
  "dome": [336, 301],
  "season": [328, 781, 271],
  "figured": [537, 661, 354, 100],
  "bitter": [769, 434, 264],
  "sugar": [431, 548, 114],
  "step": [306, 1359],
  "chilly": [305, 1272, 560],
  "cap": [447, 112],
  "jacket": [1915, 605, 840],
  "gloves": [103, 352, 568, 115],
  "colder": [1863, 264],
  "glove": [103, 352, 568],
  "warmer": [312, 114, 301, 114],
  "sun": [431, 110],
  "chase": [305, 781, 101],
  "per": [402, 114],
  "goodness": [344, 111, 100, 341, 625],
  "streets": [1844, 115],
  "slowing": [115, 352, 325, 110, 103],
  "gas": [548, 115],
  "running": [522, 110, 700, 110, 103],
  "sofa": [360, 515],
  "pipe": [952, 402],
  "bear": [345, 281],
  "yard": [2950],
  "mouse": [420, 348, 101],
  "weatherman": [371, 286, 438, 114, 407, 110],
  "tells": [479, 273, 115],
  "temperature": [479, 109, 402, 421, 2040, 354],
  "town": [2997],
  "sports": [873, 283, 1477],
  "shows": [313, 926, 115],
  "fighting": [537, 340, 355, 110, 103],
  "kid": [1713, 100],
  "reporters": [354, 455, 114, 479, 114, 115],
  "computers": [2660, 479, 114, 115],
  "online": [271, 309, 341],
  "internet": [261, 479, 114, 341, 116],
  "amazing": [1005, 97, 122, 279],
  "travel": [1825, 97, 568, 108],
  "china": [2264, 97],
  "stood": [306, 1416],
  "wall": [312, 273],
  "beatles": [345, 286, 327, 115],
  "musical": [538, 763, 447, 108],
  "group": [1957, 259, 112],
  "sing": [763, 110, 103],
  "song": [360, 110, 103],
  "crowds": [1899, 119, 100, 115],
  "early": [290, 114, 560],
  "wants": [312, 110, 1477],
  "pursuit": [572, 114, 431, 287],
  "happyness": [2701, 341, 625],
  "based": [442, 328, 100],
  "ending": [282, 308, 110, 103],
  "sit": [763, 116],
  "starbucks": [636, 323, 605, 115],
  "common": [394, 1653, 271],
  "sniff": [115, 700, 563],
  "bill": [769, 273],
  "easter": [290, 306, 264],
  "homeless": [1036, 327, 625],
  "wheelchairs": [318, 101, 949, 305, 1635, 115],
  "color": [394, 352, 114],
  "actors": [1589, 363, 114, 115],
  "curse": [676, 114, 328],
  "violence": [551, 111, 327, 110, 527],
  "action": [1589, 812],
  "pbs": [112, 98, 115],
  "public": [572, 98, 309, 99],
  "broadcasting": [1104, 111, 823, 447, 306, 279],
  "system": [115, 121, 306, 1495],
  "puts": [572, 1477],
  "gardening": [548, 114, 719, 700, 110, 103],
  "follows": [2562, 115],
  "knitting": [107, 700, 434, 279],
  "dozen": [336, 122, 282],
  "adding": [823, 308, 110, 103],
  "donate": [336, 1136, 479],
  "judge": [3290, 100, 375],
  "judy": [3290, 3299],
  "lawsuits": [439, 119, 431, 287, 115],
  "complained": [2895, 609],
  "ebay": [101, 442, 121],
  "works": [1056, 114, 107, 115],
  "seller": [2406, 264],
  "buyer": [323, 534, 114],
  "singer": [763, 110, 375, 114],
  "difference": [909, 282, 527],
  "singers": [763, 110, 375, 114, 115],
  "cd": [99, 100],
  "cds": [99, 100, 115],
  "stations": [306, 979, 115],
  "occur": [2020, 676, 114],
  "signal": [2240, 1136, 108],
  "single": [763, 110, 103, 327],
  "channel": [2498],
  "cable": [447, 595],
  "antenna": [267, 479, 110, 1136],
  "rabbit": [421, 98, 769, 116],
  "ears": [290, 114, 115],
  "strong": [306, 365, 110, 103],
  "interested": [261, 479, 354, 306, 609],
  "personality": [402, 114, 360, 1136, 309, 930],
  "uh-oh": [117, 104, 45, 1152],
  "weighs": [371, 105, 340, 115],
  "french": [1756, 282, 305],
  "snails": [115, 2134, 115],
  "cat-eyes": [447, 116, 45, 2565, 285],
  "sight": [763, 491],
  "caught": [447, 2837, 104, 116],
  "hug": [1965, 103],
  "mood": [420, 111, 100],
  "boobs": [634, 111, 98, 115],
  "tonight": [363, 1170],
  "blind": [98, 309, 110, 100],
  "standing": [3160, 308, 110, 103],
  "behind": [345, 489, 110, 100],
  "checkout": [2438, 579],
  "pineapples": [952, 341, 2421, 2656],
  "gotten": [344, 434, 282],
  "shelf": [313, 949, 102],
  "fact": [515, 577],
  "jazz": [1915, 1447],
  "club": [99, 658, 98],
  "pleasant": [1498, 422, 110, 116],
  "chemistry": [305, 1495, 492, 1825, 121],
  "worst": [1056, 114, 306],
  "taxi": [1964, 105],
  "meal": [301, 367],
  "tip": [355, 112],
  "blame": [1199, 301],
  "act": [1589, 116],
  "dating": [1731, 355, 110, 103],
  "hobby": [334, 98, 2859],
  "furthest": [835, 114, 258, 1200],
  "trade": [1825, 823, 101],
  "laughed": [439, 2837, 438, 100],
  "noses": [1157, 115],
  "good-looking": [344, 111, 100, 45, 352, 526, 279],
  "good-smelling": [344, 111, 100, 45, 2378, 279],
  "sensitive": [328, 110, 763, 355, 568],
  "odors": [111, 336, 114, 115],
  "drugs": [1913, 2042],
  "sneak": [115, 341, 97, 107],
  "cigarette": [575, 548, 354, 434, 101],
  "stink": [306, 1696],
  "evening": [381, 282, 279],
  "apply": [2421, 387, 121],
  "customs": [676, 635, 109, 115],
  "chinese": [2264, 285, 101],
  "delicious": [1968, 947],
  "reservations": [354, 328, 114, 2369, 812, 115],
  "popular": [455, 572, 439, 114],
  "fast-food": [1274, 45, 2127, 111, 100],
  "slowest": [115, 352, 371, 306],
  "cook": [394, 526],
  "burger": [1138, 375, 114],
  "workers": [1056, 114, 466, 114, 115],
  "soup": [360, 692],
  "tomato": [363, 407, 363],
  "tasted": [2157, 609],
  "lemon": [327, 420, 110],
  "butter": [2158],
  "bacon": [442, 394, 110],
  "sandwiches": [422, 110, 100, 325, 305, 285],
  "toast": [363, 781, 116],
  "pickles": [952, 605, 327, 115],
  "rice": [335, 527],
  "waiter": [929, 264],
  "steak": [1830, 107],
  "spit": [1630],
  "smile": [115, 543, 327],
  "brings": [1104, 261, 2042],
  "hands": [274, 110, 100, 115],
  "fingernails": [537, 110, 375, 114, 2134, 115],
  "nails": [2134, 115],
  "disgusting": [308, 115, 661, 306, 279],
  "poured": [455, 467, 609],
  "yuck": [121, 117, 605],
  "cooks": [394, 526, 115],
  "charge": [305, 281, 375],
  "eating": [290, 355, 110, 103],
  "piece": [952, 101, 527],
  "serve": [328, 114, 568],
  "main": [407, 261],
  "tables": [445, 595, 115],
  "chairs": [305, 1635, 115],
  "silverware": [763, 108, 568, 114, 312, 354],
  "passes": [3188, 285],
  "inspection": [261, 873, 101, 577, 1937],
  "forgetting": [2127, 114, 375, 434, 279],
  "examine": [689, 1005, 3009],
  "germs": [375, 114, 109, 115],
  "focus": [2127, 676, 115],
  "oops": [294, 2083],
  "manager": [407, 1136, 375, 114],
  "drinks": [905, 110, 107, 115],
  "send": [328, 110, 100],
  "immediately": [1094, 1716, 286, 949, 121],
  "adventure": [823, 568, 110, 2040, 354],
  "table": [445, 595],
  "door": [1847],
  "bar": [442, 114],
  "sat": [422, 116],
  "andy": [267, 3299],
  "warhol": [312, 114, 334, 108],
  "butterflies": [2158, 2442, 285],
  "flower": [1783, 371, 114],
  "napkin": [2579, 1713, 110],
  "stains": [2727, 115],
  "peanuts": [1841, 1477],
  "foul": [2127, 117, 108],
  "ball": [1616],
  "golf": [2855],
  "silly": [763, 273, 121],
  "certainly": [527, 114, 2271, 560],
  "ground": [1957, 1363],
  "holes": [334, 327, 115],
  "golfers": [2855, 1069],
  "mental": [301, 110, 445, 108],
  "nuts": [1159, 1477],
  "fishing": [2582, 279],
  "river": [335, 568, 114],
  "lake": [439, 466],
  "rods": [365, 100, 115],
  "bait": [442, 287],
  "bases": [442, 328, 115],
  "slide": [1828, 719],
  "yankees": [121, 267, 466, 285],
  "dodgers": [336, 100, 375, 114, 115],
  "practice": [2381, 577, 396, 101],
  "boring": [634, 335, 110, 103],
  "jogging": [586, 103, 556, 110, 103],
  "tiger": [355, 375, 114],
  "greatest": [1957, 290, 479, 306],
  "golfer": [2855, 264],
  "scuba": [115, 676, 442],
  "drown": [1781, 877],
  "retires": [354, 355, 354, 115],
  "dives": [308, 568, 115],
  "relax": [2699, 120],
  "nervous": [341, 114, 784, 348],
  "tournament": [363, 467, 1136, 301, 110, 116],
  "sank": [422, 110, 107],
  "foot": [2127, 111, 116],
  "putt": [572, 434],
  "stroke": [306, 365, 466],
  "footer": [2127, 111, 479, 114],
  "outer": [259, 479, 114],
  "human": [1965, 407, 110],
  "possibly": [2178, 98, 560],
  "shot": [550, 116],
  "mars": [407, 114, 115],
  "babe": [442, 345],
  "ruth": [522, 258],
  "changed": [2260, 100],
  "hospitals": [2465, 115],
  "cheer": [733, 264],
  "punched": [572, 110, 305, 609],
  "argument": [281, 661, 301, 110, 116],
  "victim": [551, 577, 1094],
  "concrete": [394, 110, 1835, 479],
  "steps": [306, 1359, 115],
  "tickets": [355, 605, 840, 115],
  "cheaper": [1840, 402, 114],
  "outfield": [579, 537, 949, 100],
  "hitting": [489, 434, 279],
  "amateur": [1005, 1543, 467],
  "arm": [281, 109],
  "follow": [2562],
  "hitter": [489, 434, 264],
  "personal": [402, 114, 360, 1136, 108],
  "apologized": [2421, 111, 352, 556, 122, 609],
  "fans": [515, 110, 115],
  "league": [327, 97, 661, 101],
  "suspended": [431, 873, 282, 719, 100],
  "figures": [537, 661, 354, 115],
  "crime": [1264, 301],
  "neighborhood": [2058, 634, 114, 334, 111, 100],
  "sidewalks": [763, 719, 1478, 115],
  "moves": [420, 568, 115],
  "burned": [1138, 341, 100],
  "smoking": [1118, 1713, 110, 103],
  "smoke": [1118, 466],
  "alarm": [367, 281, 109],
  "fifteen": [537, 102, 479, 282],
  "fires": [2468, 115],
  "law": [439, 119],
  "firebug": [2468, 323, 103],
  "sense": [328, 110, 328],
  "latest": [439, 479, 306],
  "charged": [305, 281, 375, 100],
  "murder": [538, 114, 719, 114],
  "seatbelt": [1818, 345, 2417],
  "protect": [530, 479, 577],
  "uncomfortable": [390, 749, 2127, 114, 445, 595],
  "tight": [355, 491],
  "breathe": [1104, 290, 321],
  "breath": [1104, 290, 258],
  "bulb": [323, 108, 98],
  "burnt": [1138, 110, 116],
  "dictionaries": [308, 577, 1937, 2262, 285],
  "textbooks": [479, 120, 116, 634, 526, 115],
  "slip": [1828, 112],
  "fall": [515, 273],
  "holding": [334, 498, 279],
  "breaks": [1104, 290, 107, 115],
  "pieces": [952, 101, 527, 115],
  "rest": [354, 306],
  "stepladder": [306, 1359, 439, 100, 719, 114],
  "puddle": [572, 100, 100, 327],
  "clean-up": [1054, 45, 692],
  "slick": [1828, 605],
  "floors": [2864, 115],
  "slips": [1828, 2083],
  "crack": [1122, 605],
  "orange": [283, 1941],
  "cone": [394, 341],
  "cones": [394, 341, 115],
  "mop": [420, 112],
  "rings": [335, 110, 2042],
  "quickly": [845, 1006, 560],
  "north": [293, 114, 258],
  "rosters": [365, 306, 1069],
  "roll": [365, 273],
  "building": [323, 1272, 308, 110, 103],
  "fireman": [2468, 407, 110],
  "upstairs": [692, 2192, 465, 115],
  "stove": [635, 568],
  "burner": [1138, 341, 114],
  "buying": [2288, 279],
  "guns": [661, 110, 115],
  "gun": [661, 110],
  "questions": [1992, 115],
  "receipt": [354, 527, 2924, 116],
  "america": [1005, 264, 396, 97],
  "article": [2962],
  "mayor": [407, 121, 283],
  "rate": [421, 479],
  "lock": [352, 605],
  "doors": [1847, 115],
  "believes": [885, 381, 285],
  "earthquakes": [290, 114, 258, 845, 97, 466, 115],
  "recent": [354, 527, 110, 116],
  "destroyed": [719, 306, 365, 534, 100],
  "homes": [1036, 115],
  "safer": [422, 463, 114],
  "florida": [1783, 335, 1731],
  "hurricanes": [1965, 114, 335, 447, 341, 115],
  "june": [3290, 341],
  "october": [2607, 345, 114],
  "harmless": [721, 109, 327, 625],
  "hurricane": [1965, 114, 335, 447, 341],
  "andrew": [653, 354, 119],
  "hawaii": [274, 2647, 105],
  "vacation": [2369, 447, 812],
  "island": [492, 439, 110, 100],
  "swimming": [1662, 1094, 543, 110, 103],
  "sunny": [431, 110, 110, 121],
  "breakfast": [1104, 290, 107, 1274],
  "eggs": [101, 103, 2042],
  "sausage": [422, 348, 1887],
  "juice": [3290, 396, 101],
  "nights": [700, 340, 1477],
  "allow": [367, 1449],
  "pets": [402, 1477],
  "sleeping": [2402, 279],
  "sheet": [3296],
  "leaves": [327, 97, 568, 115],
  "airport": [1635, 455, 114, 116],
  "freeways": [1756, 101, 101, 615, 115],
  "least": [327, 781, 116],
  "fly": [102, 560],
  "york": [121, 283, 107],
  "during": [2653, 335, 110, 103],
  "christmas": [305, 335, 306, 407, 115],
  "holidays": [334, 309, 1731, 121, 115],
  "march": [407, 114, 305],
  "selling": [2406, 279],
  "flown": [1783, 877],
  "prices": [2152, 115],
  "jammed": [1915, 1653, 609],
  "coughing": [394, 2837, 489, 110, 103],
  "sneezing": [115, 2342, 122, 279],
  "elbow": [949, 634, 119],
  "knee": [107, 2342],
  "crying": [99, 685, 279],
  "climbing": [99, 309, 809, 279],
  "zoo": [122, 294],
  "rowed": [365, 371, 100],
  "across": [1589, 365, 625],
  "atlantic": [286, 439, 110, 355, 99],
  "break": [1104, 290, 107],
  "lasts": [439, 306, 115],
  "paid": [557, 470],
  "cruise": [3005, 492, 101],
  "ship": [313, 2924],
  "depends": [719, 402, 110, 100, 115],
  "cabin": [447, 769, 110],
  "storms": [903, 109, 115],
  "view": [551, 101, 119],
  "sister": [763, 306, 264],
  "security": [328, 676, 335, 930],
  "hurts": [1965, 114, 1477],
  "land": [439, 110, 100],
  "altitude": [367, 355, 2040, 719],
  "earplugs": [290, 114, 387, 2837, 115],
  "spring": [873, 335, 110, 103],
  "arizona": [2262, 122, 271, 97],
  "grand": [1957, 653],
  "canyon": [447, 110, 121, 271],
  "mule": [538, 327],
  "trail": [1825, 97, 1272],
  "fallen": [515, 273, 282],
  "walls": [312, 273, 115],
  "thin": [395],
  "tvs": [808, 115],
  "telephones": [479, 327, 907, 271, 285],
  "snoring": [115, 293, 335, 110, 103],
  "housekeeping": [334, 348, 101, 466, 1359, 279],
  "nonsmoking": [293, 110, 1118, 1713, 110, 103],
  "stunk": [306, 390, 107],
  "elevator": [949, 381, 286, 283],
  "ice": [396, 101],
  "added": [823, 719, 100],
  "phony": [907, 271, 121],
  "charges": [305, 281, 375, 115],
  "agent": [1887, 110, 116],
  "discount": [308, 115, 394, 390, 116],
  "falling": [515, 273, 279],
  "bomb": [634, 809],
  "threat": [258, 354, 286],
  "stuck": [968, 605],
  "someday": [468, 1731, 121],
  "washington": [2266, 279, 363, 110],
  "c": [99],
  "invited": [261, 551, 1551],
  "veterans": [568, 479, 421, 110, 115],
  "private": [1241, 2369, 479],
  "organization": [283, 548, 700, 122, 979],
  "soldiers": [360, 498, 105, 1069],
  "served": [328, 114, 568, 100],
  "ii": [105, 105],
  "monument": [420, 1159, 301, 110, 116],
  "donations": [336, 1136, 812, 115],
  "flight": [2442, 491],
  "pictures": [952, 577, 467, 285],
  "band": [442, 110, 100],
  "honor": [334, 293, 114],
  "deserve": [719, 328, 114, 568],
  "country": [394, 390, 1825, 121],
  "laid": [439, 470],
  "coworkers": [394, 1056, 114, 466, 114, 115],
  "newspaper": [855, 873, 2421, 264],
  "interview": [261, 479, 114, 551, 101, 119],
  "double-check": [336, 117, 595, 45, 2438],
  "teeth": [479, 840, 104],
  "shine": [313, 3009],
  "shined": [313, 261, 609],
  "socks": [360, 605, 115],
  "match": [407, 116, 305],
  "dark": [1731, 114, 107],
  "babysitter": [442, 2859, 763, 434, 264],
  "babies": [442, 769, 285],
  "diapers": [308, 2421, 1069],
  "painter": [557, 261, 479, 114],
  "handyman": [274, 110, 3299, 407, 110],
  "dripping": [905, 493, 279],
  "faucet": [515, 117, 527, 116],
  "parts": [557, 114, 1477],
  "skills": [115, 1713, 273, 115],
  "flip": [2442, 112],
  "hamburgers": [274, 809, 467, 375, 114, 115],
  "layoffs": [439, 121, 789, 102, 115],
  "place": [387, 1589, 101],
  "flipping": [2442, 493, 279],
  "king": [1713, 110, 103],
  "jobs": [729, 115],
  "become": [345, 1076],
  "part": [557, 114, 116],
  "finished": [537, 700, 313, 609],
  "routine": [365, 1375, 341],
  "repeat": [354, 402, 286],
  "yells": [534, 273, 115],
  "jerk": [106, 2922],
  "report": [354, 455, 114, 116],
  "supervisor": [431, 402, 114, 551, 360, 114],
  "troublemakers": [1825, 259, 595, 407, 466, 114, 115],
  "complainers": [2895, 1069],
  "making": [407, 1713, 110, 103],
  "salary": [422, 439, 685],
  "choose": [555, 328],
  "happiness": [603, 1933, 115],
  "sell": [2406],
  "lighters": [309, 340, 479, 114, 115],
  "fortune": [2127, 114, 2040, 341],
  "guarantees": [661, 281, 267, 479, 285],
  "stock": [306, 2020, 107],
  "buys": [2288, 115],
  "hunch": [1965, 110, 305],
  "company": [749, 557, 110, 121],
  "savings": [422, 551, 110, 2042],
  "basket": [2958],
  "f": [102],
  "tutor": [2040, 363, 114],
  "killer": [1713, 273, 264],
  "doctors": [1296, 115],
  "patients": [557, 355, 282, 1477],
  "carrier": [447, 114, 335, 264],
  "exercise": [689, 264, 575, 328],
  "pet": [2314],
  "unfriendly": [390, 1756, 105, 578, 560],
  "knock": [430, 605],
  "corporations": [394, 114, 455, 421, 812, 115],
  "knocking": [430, 605, 279],
  "sore": [360, 354],
  "knuckles": [107, 1159, 605, 327, 115],
  "salads": [422, 439, 100, 115],
  "lettuce": [2414, 117, 527],
  "celery": [527, 327, 685],
  "pepper": [2278, 264],
  "salt": [422, 2417],
  "dressing": [100, 354, 625, 279],
  "calories": [447, 352, 335, 285],
  "cows": [2313, 115],
  "milk": [2334, 107],
  "leather": [327, 286, 438, 114],
  "cow": [2313],
  "deli": [1859],
  "ate": [1543],
  "meat": [301, 286],
  "customer": [676, 635, 301, 114],
  "ordered": [283, 719, 354, 100],
  "sliced": [1828, 2348],
  "huh": [1965, 104],
  "diet": [308, 840],
  "switched": [1662, 1460, 609],
  "pasta": [557, 2192],
  "potatoes": [455, 445, 363, 285],
  "processed": [530, 527, 625, 609],
  "natural": [1136, 2040, 421, 108],
  "vitamins": [551, 445, 543, 110, 115],
  "prepare": [702, 557, 354],
  "steam": [1830, 109],
  "cans": [447, 110, 115],
  "sauce": [422, 117, 527],
  "sprinkled": [873, 335, 110, 107, 327, 100],
  "feelings": [463, 949, 261, 2042],
  "fruits": [1756, 117, 287, 115],
  "banana": [442, 1136, 1136],
  "pink": [952, 110, 107],
  "peeled": [402, 949, 609],
  "sticker": [306, 396, 466, 114],
  "navel": [1136, 568, 108],
  "bananas": [442, 1136, 1136, 115],
  "roasted": [365, 781, 1551],
  "salted": [422, 2417, 609],
  "boiled": [634, 1272, 609],
  "boil": [634, 1272],
  "raw": [421, 119],
  "shells": [313, 949, 108, 115],
  "soft": [360, 102, 116],
  "brother": [1104, 1628],
  "allergic": [367, 327, 114, 556, 99],
  "strict": [306, 335, 577],
  "gaining": [1127, 279],
  "weight": [371, 1981],
  "gained": [1127, 609],
  "filled": [537, 273, 609],
  "freezer": [1756, 101, 101, 122, 264],
  "losing": [352, 763, 110, 103],
  "stuffed": [968, 563, 609],
  "leftovers": [1190, 363, 568, 114, 115],
  "disappear": [308, 422, 493, 290, 114],
  "reheated": [354, 2683, 609],
  "burst": [1138, 306],
  "loosen": [352, 111, 328, 110],
  "belt": [345, 2417],
  "loosened": [352, 111, 328, 341, 100],
  "unbuttoned": [390, 1063, 271, 609],
  "carton": [447, 114, 363, 110],
  "promise": [530, 543, 328],
  "tag": [445, 103],
  "clerk": [665, 114, 107],
  "fit": [537, 116],
  "kept": [466, 112, 116],
  "pound": [455, 943],
  "waist": [312, 492, 116],
  "bigger": [1944, 375, 114],
  "elastic": [949, 781, 355, 99],
  "waistband": [312, 492, 116, 442, 110, 100],
  "list": [1082],
  "nonfat": [293, 110, 515, 116],
  "swiss": [1662, 492, 115],
  "purse": [572, 114, 328],
  "purses": [572, 114, 328, 115],
  "stronger": [306, 365, 110, 375, 114],
  "google": [344, 111, 103, 327],
  "search": [328, 281, 305],
  "handle": [274, 110, 100, 327],
  "markets": [407, 114, 466, 1477],
  "offering": [789, 463, 335, 110, 103],
  "shoppers": [550, 493, 1069],
  "produce": [530, 2653, 527],
  "bills": [769, 273, 115],
  "deals": [719, 367, 115],
  "usual": [348, 117, 367],
  "large": [439, 114, 375],
  "one-pound": [440, 45, 455, 943],
  "charity": [305, 281, 2930],
  "desktop": [719, 115, 107, 363, 112],
  "pc": [2662],
  "mac": [407, 99],
  "macs": [407, 99, 115],
  "pcs": [2662, 115],
  "anytime": [590, 597],
  "ripped": [335, 493, 609],
  "solution": [1743, 812],
  "site": [763, 479],
  "sent": [328, 110, 116],
  "credit": [1835, 308, 116],
  "pencil": [402, 110, 575, 108],
  "sharpener": [313, 281, 402, 341, 114],
  "sharpen": [313, 281, 402, 110],
  "dining": [308, 700, 110, 103],
  "sharpeners": [313, 281, 402, 341, 114, 115],
  "legs": [327, 2042],
  "rubber": [522, 98, 345, 114],
  "suction": [431, 577, 1937],
  "cups": [676, 2083],
  "stretch": [1750, 116, 305],
  "saves": [422, 568, 115],
  "bag": [442, 103],
  "mixed": [543, 120, 609],
  "tastes": [2157, 285],
  "cash": [447, 313],
  "monthly": [420, 110, 258, 560],
  "payments": [557, 121, 301, 110, 1477],
  "peanut": [1841, 116],
  "corner": [394, 114, 341, 114],
  "inside": [261, 763, 719],
  "intersection": [261, 479, 114, 328, 577, 1937],
  "collision": [1600, 492, 1937],
  "less": [327, 625],
  "unit": [390, 287],
  "sides": [763, 719, 115],
  "allowed": [367, 352, 371, 100],
  "barking": [442, 114, 1713, 110, 103],
  "units": [390, 287, 115],
  "checkbook": [2438, 634, 526],
  "rent": [354, 110, 116],
  "doorbell": [1847, 345, 273],
  "visitors": [551, 763, 363, 114, 115],
  "bedrooms": [1671, 365, 111, 109, 115],
  "bathrooms": [442, 258, 365, 111, 109, 115],
  "afraid": [775, 421, 470],
  "road": [365, 823],
  "heated": [2683, 609],
  "survive": [431, 114, 551, 568],
  "fireplaces": [2468, 387, 1589, 285],
  "wood": [1056, 111, 100],
  "quiet": [845, 105, 840],
  "weekends": [814, 466, 110, 100, 115],
  "lawns": [439, 877, 115],
  "rusty": [522, 306, 121],
  "yards": [2950, 115],
  "property": [530, 402, 114, 930],
  "values": [2369, 658, 285],
  "council": [394, 390, 575, 108],
  "barbara": [442, 114, 442, 421],
  "loses": [352, 328, 115],
  "bears": [345, 281, 115],
  "invading": [261, 2369, 308, 110, 103],
  "neighborhoods": [2058, 634, 114, 334, 111, 100, 115],
  "starving": [636, 551, 110, 103],
  "woods": [1056, 111, 100, 115],
  "belong": [345, 352, 110, 103],
  "grass": [1957, 781, 115],
  "berries": [345, 114, 335, 285],
  "round": [365, 943],
  "cover": [394, 568, 114],
  "trash": [1825, 781, 104],
  "solve": [1767, 568],
  "shooting": [2953, 355, 110, 103],
  "vote": [784, 479],
  "voted": [784, 1551],
  "obama": [2960],
  "president": [702, 763, 719, 110, 116],
  "speaker": [2181, 466, 114],
  "election": [949, 101, 577, 1937],
  "voting": [784, 355, 110, 103],
  "promises": [530, 543, 328, 115],
  "promised": [530, 543, 328, 100],
  "officers": [789, 537, 527, 114, 115],
  "liar": [309, 281],
  "voters": [784, 479, 114, 115],
  "votes": [784, 479, 115],
  "ballot": [1616, 111, 116],
  "taxes": [1964, 285],
  "closed": [818, 328, 100],
  "bowling": [634, 119, 309, 110, 103],
  "alley": [367, 327, 121],
  "helps": [1020, 2083],
  "relaxed": [2699, 120, 609],
  "leaders": [327, 823, 1069],
  "leads": [327, 823, 115],
  "mccain": [2700, 447, 261],
  "imagine": [1094, 97, 556, 341],
  "stress": [1750, 625],
  "power": [455, 371, 114],
  "spends": [873, 578, 115],
  "duties": [2653, 355, 285],
  "traveling": [1825, 97, 568, 309, 110, 103],
  "visiting": [551, 763, 355, 110, 103],
  "cities": [575, 355, 285],
  "raising": [421, 492, 279],
  "reelection": [354, 949, 101, 577, 1937],
  "reelected": [354, 949, 101, 577, 609],
  "ralph": [421, 108, 907],
  "nader": [1136, 719, 114],
  "hates": [274, 479, 115],
  "democrats": [719, 420, 1122, 1477],
  "republicans": [354, 572, 98, 309, 447, 110, 115],
  "candidate": [447, 110, 308, 1731, 479],
  "chance": [1256, 527],
  "unless": [390, 327, 625],
  "elected": [949, 101, 577, 609],
  "office": [789, 537, 527],
  "senator": [328, 1136, 363, 114],
  "officials": [789, 537, 575, 367, 115],
  "possible": [2966],
  "explain": [689, 1123, 261],
  "honest": [334, 341, 306],
  "democratic": [719, 420, 1122, 355, 99],
  "former": [2127, 114, 301, 114],
  "bush": [323, 313],
  "conference": [394, 110, 463, 354, 110, 527],
  "american": [1005, 264, 396, 267],
  "overseas": [111, 568, 114, 328, 781],
  "wounded": [1056, 390, 719, 100],
  "spoke": [873, 526, 101],
  "soldier": [360, 498, 105, 264],
  "plenty": [387, 282, 930],
  "official": [789, 537, 575, 367],
  "sample": [422, 109, 387, 101],
  "voter": [784, 479, 114],
  "instructions": [2715, 577, 1937, 115],
  "cent": [527, 110, 116],
  "against": [1222, 306],
  "highways": [489, 340, 615, 115],
  "prisons": [1241, 360, 110, 115],
  "legislators": [327, 556, 115, 439, 363, 114, 115],
  "spent": [873, 570],
  "first-class": [537, 114, 306, 45, 2463, 625],
  "giving": [556, 551, 110, 103],
  "measures": [301, 781, 467, 285],
  "improve": [1094, 530, 568],
  "roads": [365, 823, 115],
  "raise": [421, 492, 101],
  "ads": [823, 115],
  "increase": [261, 1835, 781, 101],
  "opposite": [111, 493, 111, 763, 479],
  "title": [355, 116, 327],
  "measure": [301, 781, 467, 101],
  "lie": [309, 101],
  "politicians": [1238, 355, 575, 267, 115],
  "cereal": [527, 354, 367],
  "stain": [2727],
  "blood": [98, 352, 111, 100],
  "bleeding": [595, 609, 279],
  "ruined": [522, 261, 609],
  "soak": [360, 97, 107],
  "fingers": [537, 110, 375, 114, 115],
  "typing": [930, 952, 110, 103],
  "causing": [447, 348, 279],
  "pain": [557, 261],
  "bone": [634, 341],
  "cancer": [447, 110, 527, 114],
  "causes": [447, 348, 285],
  "stomachaches": [1971, 305, 1589, 438, 115],
  "positive": [455, 763, 355, 568],
  "medication": [1716, 447, 812],
  "sand": [422, 110, 100],
  "finger": [537, 110, 375, 114],
  "band-aids": [442, 110, 100, 45, 97, 470, 115],
  "band-aid": [442, 110, 100, 45, 97, 470],
  "heals": [438, 367, 115],
  "heal": [438, 367],
  "stinks": [306, 1696, 115],
  "sidewalk": [763, 719, 1478],
  "smokers": [1118, 466, 114, 115],
  "weak": [371, 97, 107],
  "controls": [394, 110, 1825, 111, 108, 115],
  "puff": [572, 563],
  "taken": [445, 466, 110],
  "drops": [1781, 2083],
  "suntan": [431, 110, 445, 110],
  "lotion": [352, 812],
  "tan": [445, 110],
  "pale": [557, 327],
  "skin": [115, 1713, 110],
  "arguing": [281, 661, 279],
  "smoker": [1118, 466, 114],
  "surgery": [431, 114, 375, 685],
  "insurance": [261, 431, 421, 110, 527],
  "rub": [522, 98],
  "smokes": [1118, 466, 115],
  "packs": [557, 605, 115],
  "chain": [305, 97, 261],
  "unbelievable": [390, 885, 381, 922],
  "alive": [367, 105, 568],
  "heart": [827, 116],
  "lungs": [658, 110, 2042],
  "healthy": [438, 367, 258, 121],
  "brushing": [1104, 348, 489, 110, 103],
  "chore": [305, 283, 101],
  "brush": [1104, 348, 104],
  "brushed": [1104, 348, 438, 100],
  "floss": [1783, 625],
  "invented": [261, 568, 110, 1551],
  "flossing": [1783, 625, 279],
  "dentist": [719, 110, 355, 306],
  "climb": [99, 309, 809],
  "wild": [325, 498],
  "lizards": [309, 122, 1869, 115],
  "hiking": [489, 1713, 110, 103],
  "goats": [344, 286, 115],
  "sweat": [1662, 290, 116],
  "hike": [489, 466],
  "pimple": [952, 109, 387, 101],
  "pimples": [952, 109, 2656],
  "genes": [375, 341, 115],
  "pollution": [455, 273, 1375, 271],
  "cause": [447, 348, 101],
  "bright": [1104, 1981],
  "side": [763, 719],
  "pop": [455, 112],
  "newspapers": [855, 873, 2421, 1069],
  "stories": [903, 105, 285],
  "government": [344, 568, 114, 110, 301, 110, 116],
  "fourth": [2127, 467, 258],
  "swine": [1662, 3009],
  "flu": [102, 658],
  "mexico": [301, 120, 396, 111],
  "frequently": [1756, 101, 845, 570, 560],
  "picking": [952, 605, 279],
  "scratching": [115, 1122, 116, 2264, 103],
  "emergency": [1495, 264, 375, 110, 1984],
  "remote": [354, 420, 479],
  "filthy": [537, 2417, 104, 121],
  "covered": [394, 568, 354, 100],
  "crud": [3005, 100],
  "damp": [1731, 109, 112],
  "cloth": [818, 258],
  "cracks": [1122, 605, 115],
  "squeeze": [115, 845, 101, 101, 122, 101],
  "firmly": [537, 114, 109, 560],
  "planes": [1074, 285],
  "swelling": [1662, 949, 309, 110, 103],
  "normal": [293, 114, 407, 108],
  "bless": [595, 625],
  "modern": [420, 719, 114, 110],
  "aches": [1589, 438, 115],
  "right-handed": [646, 45, 274, 110, 719, 100]
}
